src/__init__.py
src/config.py
src/dev_main.py
src/main.py
src/tools.py
src/weaviate_client.py
mcp_weaviate-0.2.0.dist-info/METADATA
mcp_weaviate-0.2.0.dist-info/WHEEL
mcp_weaviate-0.2.0.dist-info/entry_points.txt
mcp_weaviate-0.2.0.dist-info/licenses/LICENSE
mcp_weaviate-0.2.0.dist-info/RECORD
