Metadata-Version: 2.4
Name: mcp-weaviate
Version: 0.2.0
Summary: MCP server for Weaviate vector database operations
License-File: LICENSE
Requires-Python: >=3.12
Requires-Dist: click>=8.2.1
Requires-Dist: fastmcp>=2.11.3
Requires-Dist: pydantic>=2.0.0
Requires-Dist: python-dotenv>=1.1.1
Requires-Dist: weaviate-client>=4.16.9
Provides-Extra: dev
Requires-Dist: mypy>=1.7.0; extra == 'dev'
Requires-Dist: pre-commit>=3.0.0; extra == 'dev'
Requires-Dist: pytest-asyncio>=0.21.0; extra == 'dev'
Requires-Dist: pytest-mock>=3.0.0; extra == 'dev'
Requires-Dist: pytest>=7.0.0; extra == 'dev'
Requires-Dist: ruff>=0.1.0; extra == 'dev'
